xaal/__init__.py
xaal/legacytools/__init__.py
xaal/legacytools/ansi2.py
xaal/legacytools/dumper.py
xaal/legacytools/info.py
xaal/legacytools/inspector.py
xaal/legacytools/isalive.py
xaal/legacytools/keygen.py
xaal/legacytools/log.py
xaal/legacytools/pkgrun.py
xaal/legacytools/querydb.py
xaal/legacytools/tail.py
xaal/legacytools/uuidgen.py
xaal/legacytools/walker.py
xaal_legacytools-0.3.2.dist-info/METADATA
xaal_legacytools-0.3.2.dist-info/WHEEL
xaal_legacytools-0.3.2.dist-info/entry_points.txt
xaal_legacytools-0.3.2.dist-info/top_level.txt
xaal_legacytools-0.3.2.dist-info/RECORD
