Metadata-Version: 2.4
Name: xaal.legacytools
Version: 0.3.2
Summary: xAAL devices tools (legacy)
Author-email: Jerome Kerdreux <Jerome.Kerdreux@imt-atlantique.fr>
License-Expression: GPL-3.0-or-later
Project-URL: Homepage, https://recherche.imt-atlantique.fr/xaal/
Project-URL: Documentation, https://gitlab.imt-atlantique.fr/xaal/code/python/-/blob/main/apps/legacytools/README.rst
Project-URL: Source, https://gitlab.imt-atlantique.fr/xaal/code/python/-/tree/main/apps/legacytools
Keywords: xaal,tools
Classifier: Programming Language :: Python
Classifier: Topic :: Home Automation
Requires-Dist: xaal.lib
